bluesky_search/__init__.py
bluesky_search/cli.py
bluesky_search/client.py
bluesky_search/fetcher.py
bluesky_search/list.py
bluesky_search/search.py
bluesky_search/export/__init__.py
bluesky_search/export/csv.py
bluesky_search/export/json.py
bluesky_search/export/parquet.py
bluesky_search/utils/__init__.py
bluesky_search/utils/text.py
bluesky_search/utils/url.py
bluesky_search-0.1.7.dist-info/METADATA
bluesky_search-0.1.7.dist-info/WHEEL
bluesky_search-0.1.7.dist-info/entry_points.txt
bluesky_search-0.1.7.dist-info/top_level.txt
bluesky_search-0.1.7.dist-info/RECORD
