Metadata-Version: 2.2
Name: bluesky-search
Version: 0.1.7
Summary: A package to search, fetch, and export posts from Bluesky social network
Author-email: Original Author <victoriano@gmail.com>
License: MIT
Project-URL: Homepage, https://github.com/victoriano/bluesky-search
Project-URL: Bug Tracker, https://github.com/victoriano/bluesky-search/issues
Classifier: Development Status :: 3 - Alpha
Classifier: Intended Audience :: Developers
Classifier: License :: OSI Approved :: MIT License
Classifier: Programming Language :: Python :: 3
Classifier: Programming Language :: Python :: 3.8
Classifier: Programming Language :: Python :: 3.9
Classifier: Programming Language :: Python :: 3.10
Requires-Python: >=3.8
Requires-Dist: atproto>=0.0.26
Requires-Dist: polars>=0.19.2
Provides-Extra: export
Provides-Extra: dev
Requires-Dist: pytest>=6.0; extra == "dev"
Requires-Dist: black>=22.1.0; extra == "dev"
Requires-Dist: isort>=5.9.0; extra == "dev"
